{
  "id": "numpy_manipulation/add_zeros",
  "topic": "numpy_manipulation",
  "slug": "add_zeros",
  "title": "Interleave Zeros Between Elements",
  "difficulty": "easy",
  "entry": "add_zeros",
  "banned": {
    "loops": true
  },
  "statementMd": "Implement `add_zeros(x)`.\n\nGiven a 1D integer array `x`, return a new array with a single zero inserted\nbetween each pair of adjacent elements: `[1, 2, 3]` → `[1, 0, 2, 0, 3]`. An\narray with fewer than two elements is returned unchanged. No `for`/`while`\nloops — use a strided assignment.",
  "bundlePath": "/content/problems/numpy_manipulation/add_zeros",
  "pyDeps": [
    "numpy"
  ],
  "webRunnable": true,
  "hidden": false,
  "hints": [
    "Allocate a zero array of length 2*len(x)-1, then write x into every other slot with a strided assignment out[::2] = x."
  ],
  "contentHash": "57b9c7a5b300a610a7d7fe9a6dd90bd59c9cced92872566082945efe52f0916a"
}
