{
  "id": "numpy_warmup/solve_system",
  "topic": "numpy_warmup",
  "slug": "solve_system",
  "title": "Solve a Linear System",
  "difficulty": "medium",
  "entry": "solve_system",
  "banned": {
    "modules": [
      "scipy",
      "sklearn"
    ],
    "loops": true
  },
  "statementMd": "Implement `solve_system(A, b)`.\n\nGiven a square, invertible matrix `A` of shape `(n, n)` and a vector `b` of\nlength `n`, return the solution `x` of the linear system `A @ x = b`. No\n`for`/`while` loops.",
  "bundlePath": "/content/problems/numpy_warmup/solve_system",
  "pyDeps": [
    "numpy"
  ],
  "webRunnable": true,
  "hidden": true,
  "hints": [
    "np.linalg.solve(A, b) returns the x satisfying A @ x == b (don't invert A explicitly)."
  ],
  "prereqs": [],
  "next": [],
  "contentHash": "c692db2f195f8d7e604e1aa75061adff948c78bb63cf333701cb68a19a76ab41"
}
